{
    "id": "40VXD1B0",
    "name": "extension of scalars",
    "dependencies": {
        "R": "7R2CT98Y:ring",
        "S": "7R2CT98Y:ring",
        "M": "8UBME7WQ:module over {0}"
    },
    "type": {
        "8UBME7WQ": "module over {1}"
    },
    "definitions": {
        "40VXD1B0_a": {
            "language": "en",
            "dependencies": {
                "8NTXUGXG": "tensor product --of right and left modules"
            },
            "comment": ""
        }
    },
    "equivalences": {
    }
}
